diverge/__init__.py
diverge/helpers.py
diverge/libdivERGe.so
diverge/output.py
diverge_flow-0.9.1.dist-info/licenses/LICENSE.md
diverge_flow-0.9.1.dist-info/METADATA
diverge_flow-0.9.1.dist-info/WHEEL
diverge_flow-0.9.1.dist-info/top_level.txt
diverge_flow-0.9.1.dist-info/RECORD
