Metadata-Version: 2.4
Name: diverge-flow
Version: 0.9.1
Summary: divERGe implements various ERG examples
Author: Jonas B. Profe, Lennart Klebl
Author-email: jonas.hauck@rwth-aachen.de, lennart.klebl@rwth-aachen.de
License: GPLv3
Keywords: frg,hpc
Classifier: License :: OSI Approved :: GNU General Public License v3 or later (GPLv3+)
Classifier: Programming Language :: C
Classifier: Programming Language :: C++
Classifier: Environment :: GPU :: NVIDIA CUDA
Classifier: Programming Language :: Python :: 3
License-File: LICENSE.md
Requires-Dist: numpy>=1.13
Requires-Dist: setuptools>=30.3.0
Dynamic: description-content-type
Dynamic: license-file
Dynamic: requires-dist
Dynamic: summary
